README.md
setup.cfg
setup.py
everysk/__init__.py
everysk/api_requestor.py
everysk/ca-certificates.crt
everysk/http_client.py
everysk/six.py
everysk/utils.py
everysk.egg-info/PKG-INFO
everysk.egg-info/SOURCES.txt
everysk.egg-info/dependency_links.txt
everysk.egg-info/not-zip-safe
everysk.egg-info/requires.txt
everysk.egg-info/top_level.txt
everysk/api_resources/__init__.py
everysk/api_resources/api_resource.py
everysk/api_resources/calculation.py
everysk/api_resources/custom_index.py
everysk/api_resources/datastore.py
everysk/api_resources/file.py
everysk/api_resources/market_data.py
everysk/api_resources/parser.py
everysk/api_resources/portfolio.py
everysk/api_resources/private_security.py
everysk/api_resources/report.py
everysk/api_resources/report_template.py
everysk/api_resources/worker_execution.py
everysk/api_resources/workflow.py
everysk/api_resources/workflow_execution.py
everysk/api_resources/workspace.py