Metadata-Version: 2.1
Name: everysk
Version: 1.0.17
Summary: Python client for Everysk API
Home-page: https://github.com/Everysk/Everysk-API-Python
Author: Everysk Technologies
Author-email: contact@everysk.com
License: MIT
Keywords: everysk
Platform: UNKNOWN
